nonebot_plugin_splatoon3/__init__.py
nonebot_plugin_splatoon3/config.py
nonebot_plugin_splatoon3/data/__init__.py
nonebot_plugin_splatoon3/data/data_source.py
nonebot_plugin_splatoon3/data/db/image.db
nonebot_plugin_splatoon3/data/db_control.py
nonebot_plugin_splatoon3/data/db_image.py
nonebot_plugin_splatoon3/data/static_data_getter.py
nonebot_plugin_splatoon3/image/__init__.py
nonebot_plugin_splatoon3/image/image.py
nonebot_plugin_splatoon3/image/image_processer.py
nonebot_plugin_splatoon3/image/image_processer_tools.py
nonebot_plugin_splatoon3/staticData/ImageData/10024.png
nonebot_plugin_splatoon3/staticData/ImageData/10025.ico
nonebot_plugin_splatoon3/staticData/ImageData/10026.png
nonebot_plugin_splatoon3/staticData/ImageData/AREA.png
nonebot_plugin_splatoon3/staticData/ImageData/CLAM.png
nonebot_plugin_splatoon3/staticData/ImageData/Cohozuna.png
nonebot_plugin_splatoon3/staticData/ImageData/GOAL.png
nonebot_plugin_splatoon3/staticData/ImageData/Horrorboros.png
nonebot_plugin_splatoon3/staticData/ImageData/LOFT.png
nonebot_plugin_splatoon3/staticData/ImageData/Megalodontia.png
nonebot_plugin_splatoon3/staticData/ImageData/Ranked-Challenge.png
nonebot_plugin_splatoon3/staticData/ImageData/Ranked-Open.png
nonebot_plugin_splatoon3/staticData/ImageData/Ranked.png
nonebot_plugin_splatoon3/staticData/ImageData/Regular.png
nonebot_plugin_splatoon3/staticData/ImageData/TURF_WAR.png
nonebot_plugin_splatoon3/staticData/ImageData/X.png
nonebot_plugin_splatoon3/staticData/ImageData/backups/old_weapon/14式竹筒枪 •甲.jpg
nonebot_plugin_splatoon3/staticData/ImageData/backups/old_weapon/4K准星枪.jpg
nonebot_plugin_splatoon3/staticData/ImageData/backups/old_weapon/52加仑.jpg
nonebot_plugin_splatoon3/staticData/ImageData/backups/old_weapon/96加仑.jpg
nonebot_plugin_splatoon3/staticData/ImageData/backups/old_weapon/H3卷管枪.jpg
nonebot_plugin_splatoon3/staticData/ImageData/backups/old_weapon/L3卷管枪.jpg
nonebot_plugin_splatoon3/staticData/ImageData/backups/old_weapon/LACT-450.jpg
nonebot_plugin_splatoon3-1.4.3.dist-info/LICENSE
nonebot_plugin_splatoon3-1.4.3.dist-info/METADATA
nonebot_plugin_splatoon3-1.4.3.dist-info/WHEEL
nonebot_plugin_splatoon3-1.4.3.dist-info/RECORD
