Metadata-Version: 2.1
Name: nonebot-plugin-splatoon3
Version: 1.4.3
Summary: 一个基于nonebot2框架的splatoon3游戏日程查询插件
Author: cypas
Author-email: ayano05@outlook.com
Requires-Python: >=3.9,<4.0
Classifier: Programming Language :: Python :: 3
Classifier: Programming Language :: Python :: 3.9
Classifier: Programming Language :: Python :: 3.10
Classifier: Programming Language :: Python :: 3.11
Classifier: Programming Language :: Python :: 3.12
Requires-Dist: Pillow (==9.5.0)
Requires-Dist: beautifulsoup4 (>=4.12.2,<5.0.0)
Requires-Dist: cfscrape (>=2.1.1,<3.0.0)
Requires-Dist: httpx (>=0.24.1,<0.25.0)
Requires-Dist: nonebot-adapter-kaiheila (>=0.2.8,<0.3.0)
Requires-Dist: nonebot-adapter-onebot (>=2.1.3,<3.0.0)
Requires-Dist: nonebot-adapter-qq (>=1.3.4,<2.0.0)
Requires-Dist: nonebot-adapter-telegram (>=0.1.0b14,<0.2.0)
Requires-Dist: nonebot-plugin-apscheduler (>=0.3.0,<0.4.0)
Requires-Dist: nonebot2 (>=2.0.0,<3.0.0)
Requires-Dist: requests (>=2.28.2,<3.0.0)
Requires-Dist: urllib3 (==1.26.16)
